<?xml version="1.0" encoding="UTF-8"?>
<datasources xmlns="http://www.jboss.org/ironjacamar/schema">
    <datasource 
        jndi-name="syndicflowDatasource"
        enabled="true" 
        use-java-context="true" pool-name="syndicflowDatasource_pool">
        <connection-url>jdbc:postgresql://localhost:5432/syndiceo</connection-url>
        <driver>postgresql-9.2-1002.jdbc4.jar</driver>
        <security>
		      <user-name>postgres</user-name>
		      <password>postgres</password>
        </security>
    </datasource>
</datasources>
